registro/prescaler.v
module prescaler (clk_in,clk_out);
  input clk_in;
  output clk_out;
  wire clk_out;
  wire clk_in;

  parameter N = 22;

  reg [N-1 : 0] count = 0;

  always @ ( posedge clk_in) begin
    count <= count + 1;
  end

  assign clk_out = count[N-1];

endmodule //

mux2x1/mux2x1.v
module mux2x1 (clk, data);
  input wire clk;
  output reg [7:0] data;
  wire sel;
  parameter  D0 = 8'b01010101;
  parameter  D1 = 8'b10101010;
  parameter N0 = 22;

  prescaler #(.N(N0))
    PRE(
      .clk_in(clk),
      .clk_out(sel)
      );

  always @ (sel) begin
    case(sel)
    0: data = D0;
    1: data = D1;
    endcase
  end

endmodule //

mux2x1/mux2x1_tb.v
module mux2x1_tb ();
  reg clk = 0;
  wire [7:0] data;

  mux2x1 #(.N0(1))
    test(
      .clk(clk),
      .data(data)
      );

  always #1 clk = ~clk;

  initial begin
    $dumpfile("mux2x1_tb.vcd");
    $dumpvars(0,mux2x1_tb);
    #200 $display("fin de la simulacion");
    $finish;
  end

endmodule //

mux2x1/mux2x1_tb.vcd
$date
	Thu Sep 19 21:18:14 2019
$end
$version
	Icarus Verilog
$end
$timescale
	1s
$end
$scope module mux2x1_tb $end
$var wire 8 ! data [7:0] $end
$var reg 1 " clk $end
$scope module test $end
$var wire 1 " clk $end
$var wire 1 # sel $end
$var reg 8 $ data [7:0] $end
$scope module PRE $end
$var wire 1 " clk_in $end
$var wire 1 # clk_out $end
$var reg 1 % count $end
$upscope $end
$upscope $end
$upscope $end
$enddefinitions $end
#0
$dumpvars
0%
b1010101 $
0#
0"
b1010101 !
$end
#1
b10101010 !
b10101010 $
1#
1%
1"
#2
0"
#3
b1010101 !
b1010101 $
0#
0%
1"
#4
0"
#5
b10101010 !
b10101010 $
1#
1%
1"
#6
0"
#7
b1010101 !
b1010101 $
0#
0%
1"
#8
0"
#9
b10101010 !
b10101010 $
1#
1%
1"
#10
0"
#11
b1010101 !
b1010101 $
0#
0%
1"
#12
0"
#13
b10101010 !
b10101010 $
1#
1%
1"
#14
0"
#15
b1010101 !
b1010101 $
0#
0%
1"
#16
0"
#17
b10101010 !
b10101010 $
1#
1%
1"
#18
0"
#19
b1010101 !
b1010101 $
0#
0%
1"
#20
0"
#21
b10101010 !
b10101010 $
1#
1%
1"
#22
0"
#23
b1010101 !
b1010101 $
0#
0%
1"
#24
0"
#25
b10101010 !
b10101010 $
1#
1%
1"
#26
0"
#27
b1010101 !
b1010101 $
0#
0%
1"
#28
0"
#29
b10101010 !
b10101010 $
1#
1%
1"
#30
0"
#31
b1010101 !
b1010101 $
0#
0%
1"
#32
0"
#33
b10101010 !
b10101010 $
1#
1%
1"
#34
0"
#35
b1010101 !
b1010101 $
0#
0%
1"
#36
0"
#37
b10101010 !
b10101010 $
1#
1%
1"
#38
0"
#39
b1010101 !
b1010101 $
0#
0%
1"
#40
0"
#41
b10101010 !
b10101010 $
1#
1%
1"
#42
0"
#43
b1010101 !
b1010101 $
0#
0%
1"
#44
0"
#45
b10101010 !
b10101010 $
1#
1%
1"
#46
0"
#47
b1010101 !
b1010101 $
0#
0%
1"
#48
0"
#49
b10101010 !
b10101010 $
1#
1%
1"
#50
0"
#51
b1010101 !
b1010101 $
0#
0%
1"
#52
0"
#53
b10101010 !
b10101010 $
1#
1%
1"
#54
0"
#55
b1010101 !
b1010101 $
0#
0%
1"
#56
0"
#57
b10101010 !
b10101010 $
1#
1%
1"
#58
0"
#59
b1010101 !
b1010101 $
0#
0%
1"
#60
0"
#61
b10101010 !
b10101010 $
1#
1%
1"
#62
0"
#63
b1010101 !
b1010101 $
0#
0%
1"
#64
0"
#65
b10101010 !
b10101010 $
1#
1%
1"
#66
0"
#67
b1010101 !
b1010101 $
0#
0%
1"
#68
0"
#69
b10101010 !
b10101010 $
1#
1%
1"
#70
0"
#71
b1010101 !
b1010101 $
0#
0%
1"
#72
0"
#73
b10101010 !
b10101010 $
1#
1%
1"
#74
0"
#75
b1010101 !
b1010101 $
0#
0%
1"
#76
0"
#77
b10101010 !
b10101010 $
1#
1%
1"
#78
0"
#79
b1010101 !
b1010101 $
0#
0%
1"
#80
0"
#81
b10101010 !
b10101010 $
1#
1%
1"
#82
0"
#83
b1010101 !
b1010101 $
0#
0%
1"
#84
0"
#85
b10101010 !
b10101010 $
1#
1%
1"
#86
0"
#87
b1010101 !
b1010101 $
0#
0%
1"
#88
0"
#89
b10101010 !
b10101010 $
1#
1%
1"
#90
0"
#91
b1010101 !
b1010101 $
0#
0%
1"
#92
0"
#93
b10101010 !
b10101010 $
1#
1%
1"
#94
0"
#95
b1010101 !
b1010101 $
0#
0%
1"
#96
0"
#97
b10101010 !
b10101010 $
1#
1%
1"
#98
0"
#99
b1010101 !
b1010101 $
0#
0%
1"
#100
0"
#101
b10101010 !
b10101010 $
1#
1%
1"
#102
0"
#103
b1010101 !
b1010101 $
0#
0%
1"
#104
0"
#105
b10101010 !
b10101010 $
1#
1%
1"
#106
0"
#107
b1010101 !
b1010101 $
0#
0%
1"
#108
0"
#109
b10101010 !
b10101010 $
1#
1%
1"
#110
0"
#111
b1010101 !
b1010101 $
0#
0%
1"
#112
0"
#113
b10101010 !
b10101010 $
1#
1%
1"
#114
0"
#115
b1010101 !
b1010101 $
0#
0%
1"
#116
0"
#117
b10101010 !
b10101010 $
1#
1%
1"
#118
0"
#119
b1010101 !
b1010101 $
0#
0%
1"
#120
0"
#121
b10101010 !
b10101010 $
1#
1%
1"
#122
0"
#123
b1010101 !
b1010101 $
0#
0%
1"
#124
0"
#125
b10101010 !
b10101010 $
1#
1%
1"
#126
0"
#127
b1010101 !
b1010101 $
0#
0%
1"
#128
0"
#129
b10101010 !
b10101010 $
1#
1%
1"
#130
0"
#131
b1010101 !
b1010101 $
0#
0%
1"
#132
0"
#133
b10101010 !
b10101010 $
1#
1%
1"
#134
0"
#135
b1010101 !
b1010101 $
0#
0%
1"
#136
0"
#137
b10101010 !
b10101010 $
1#
1%
1"
#138
0"
#139
b1010101 !
b1010101 $
0#
0%
1"
#140
0"
#141
b10101010 !
b10101010 $
1#
1%
1"
#142
0"
#143
b1010101 !
b1010101 $
0#
0%
1"
#144
0"
#145
b10101010 !
b10101010 $
1#
1%
1"
#146
0"
#147
b1010101 !
b1010101 $
0#
0%
1"
#148
0"
#149
b10101010 !
b10101010 $
1#
1%
1"
#150
0"
#151
b1010101 !
b1010101 $
0#
0%
1"
#152
0"
#153
b10101010 !
b10101010 $
1#
1%
1"
#154
0"
#155
b1010101 !
b1010101 $
0#
0%
1"
#156
0"
#157
b10101010 !
b10101010 $
1#
1%
1"
#158
0"
#159
b1010101 !
b1010101 $
0#
0%
1"
#160
0"
#161
b10101010 !
b10101010 $
1#
1%
1"
#162
0"
#163
b1010101 !
b1010101 $
0#
0%
1"
#164
0"
#165
b10101010 !
b10101010 $
1#
1%
1"
#166
0"
#167
b1010101 !
b1010101 $
0#
0%
1"
#168
0"
#169
b10101010 !
b10101010 $
1#
1%
1"
#170
0"
#171
b1010101 !
b1010101 $
0#
0%
1"
#172
0"
#173
b10101010 !
b10101010 $
1#
1%
1"
#174
0"
#175
b1010101 !
b1010101 $
0#
0%
1"
#176
0"
#177
b10101010 !
b10101010 $
1#
1%
1"
#178
0"
#179
b1010101 !
b1010101 $
0#
0%
1"
#180
0"
#181
b10101010 !
b10101010 $
1#
1%
1"
#182
0"
#183
b1010101 !
b1010101 $
0#
0%
1"
#184
0"
#185
b10101010 !
b10101010 $
1#
1%
1"
#186
0"
#187
b1010101 !
b1010101 $
0#
0%
1"
#188
0"
#189
b10101010 !
b10101010 $
1#
1%
1"
#190
0"
#191
b1010101 !
b1010101 $
0#
0%
1"
#192
0"
#193
b10101010 !
b10101010 $
1#
1%
1"
#194
0"
#195
b1010101 !
b1010101 $
0#
0%
1"
#196
0"
#197
b10101010 !
b10101010 $
1#
1%
1"
#198
0"
#199
b1010101 !
b1010101 $
0#
0%
1"
