registro/prescaler.v
module prescaler (clk_in,clk_out);
  input clk_in;
  output clk_out;
  wire clk_out;
  wire clk_in;

  parameter N = 22;

  reg [N-1 : 0] count = 0;

  always @ ( posedge clk_in) begin
    count <= count + 1;
  end

  assign clk_out = count[N-1];

endmodule //

prescaler/prescaler_tb.v
//-- prescaler_tb.v
module prescaler_tb();

//-- Numero de bits del prescaler a comprobar
parameter N = 2;

//-- Registro para generar la señal de reloj
reg clk = 0;

//-- Salida del prescaler
wire clk_out;

//-- Registro para comprobar si el prescaler funciona
reg [N-1:0] counter_check = 0;

//-- Instanciar el prescaler de N bits
prescaler #(.N(N))  //-- Parámetro N
  Pres1(
    .clk_in(clk),
    .clk_out(clk_out)
  );

//-- Generador de reloj. Periodo 2 unidades
always #1 clk = ~clk;

//-- Comprobacion del valor del contador
//-- En cada flanco de bajada se comprueba la salida del contador
//-- y se incrementa el valor esperado
always @(negedge clk) begin

  //-- Incrementar variable del contador de prueba
  counter_check = counter_check + 1;

  //-- El bit de mayor peso debe coincidir con clk_out
  if (counter_check[N-1] != clk_out) begin
    $display("--->ERROR! Prescaler no funciona correctamente");
    $display("Clk out: %d, counter_check[2]: %d",
              clk_out, counter_check[N-1]);
  end

end

//-- Proceso al inicio
initial begin

  //-- Fichero donde almacenar los resultados
  $dumpfile("prescaler_tb.vcd");
  $dumpvars(0, prescaler_tb);

  # 99 $display("FIN de la simulacion");
  # 100 $finish;
end
endmodule

prescaler/prescaler_tb.vcd
$date
	Sat Aug 31 21:27:11 2019
$end
$version
	Icarus Verilog
$end
$timescale
	1s
$end
$scope module prescaler_tb $end
$var wire 1 ! clk_out $end
$var reg 1 " clk $end
$var reg 2 # counter_check [1:0] $end
$scope module Pres1 $end
$var wire 1 " clk_in $end
$var wire 1 ! clk_out $end
$var reg 2 $ count [1:0] $end
$upscope $end
$upscope $end
$enddefinitions $end
#0
$dumpvars
b0 $
b0 #
0"
0!
$end
#1
b1 $
1"
#2
b1 #
0"
#3
1!
b10 $
1"
#4
b10 #
0"
#5
b11 $
1"
#6
b11 #
0"
#7
0!
b0 $
1"
#8
b0 #
0"
#9
b1 $
1"
#10
b1 #
0"
#11
1!
b10 $
1"
#12
b10 #
0"
#13
b11 $
1"
#14
b11 #
0"
#15
0!
b0 $
1"
#16
b0 #
0"
#17
b1 $
1"
#18
b1 #
0"
#19
1!
b10 $
1"
#20
b10 #
0"
#21
b11 $
1"
#22
b11 #
0"
#23
0!
b0 $
1"
#24
b0 #
0"
#25
b1 $
1"
#26
b1 #
0"
#27
1!
b10 $
1"
#28
b10 #
0"
#29
b11 $
1"
#30
b11 #
0"
#31
0!
b0 $
1"
#32
b0 #
0"
#33
b1 $
1"
#34
b1 #
0"
#35
1!
b10 $
1"
#36
b10 #
0"
#37
b11 $
1"
#38
b11 #
0"
#39
0!
b0 $
1"
#40
b0 #
0"
#41
b1 $
1"
#42
b1 #
0"
#43
1!
b10 $
1"
#44
b10 #
0"
#45
b11 $
1"
#46
b11 #
0"
#47
0!
b0 $
1"
#48
b0 #
0"
#49
b1 $
1"
#50
b1 #
0"
#51
1!
b10 $
1"
#52
b10 #
0"
#53
b11 $
1"
#54
b11 #
0"
#55
0!
b0 $
1"
#56
b0 #
0"
#57
b1 $
1"
#58
b1 #
0"
#59
1!
b10 $
1"
#60
b10 #
0"
#61
b11 $
1"
#62
b11 #
0"
#63
0!
b0 $
1"
#64
b0 #
0"
#65
b1 $
1"
#66
b1 #
0"
#67
1!
b10 $
1"
#68
b10 #
0"
#69
b11 $
1"
#70
b11 #
0"
#71
0!
b0 $
1"
#72
b0 #
0"
#73
b1 $
1"
#74
b1 #
0"
#75
1!
b10 $
1"
#76
b10 #
0"
#77
b11 $
1"
#78
b11 #
0"
#79
0!
b0 $
1"
#80
b0 #
0"
#81
b1 $
1"
#82
b1 #
0"
#83
1!
b10 $
1"
#84
b10 #
0"
#85
b11 $
1"
#86
b11 #
0"
#87
0!
b0 $
1"
#88
b0 #
0"
#89
b1 $
1"
#90
b1 #
0"
#91
1!
b10 $
1"
#92
b10 #
0"
#93
b11 $
1"
#94
b11 #
0"
#95
0!
b0 $
1"
#96
b0 #
0"
#97
b1 $
1"
#98
b1 #
0"
#99
1!
b10 $
1"
#100
b10 #
0"
#101
b11 $
1"
#102
b11 #
0"
#103
0!
b0 $
1"
#104
b0 #
0"
#105
b1 $
1"
#106
b1 #
0"
#107
1!
b10 $
1"
#108
b10 #
0"
#109
b11 $
1"
#110
b11 #
0"
#111
0!
b0 $
1"
#112
b0 #
0"
#113
b1 $
1"
#114
b1 #
0"
#115
1!
b10 $
1"
#116
b10 #
0"
#117
b11 $
1"
#118
b11 #
0"
#119
0!
b0 $
1"
#120
b0 #
0"
#121
b1 $
1"
#122
b1 #
0"
#123
1!
b10 $
1"
#124
b10 #
0"
#125
b11 $
1"
#126
b11 #
0"
#127
0!
b0 $
1"
#128
b0 #
0"
#129
b1 $
1"
#130
b1 #
0"
#131
1!
b10 $
1"
#132
b10 #
0"
#133
b11 $
1"
#134
b11 #
0"
#135
0!
b0 $
1"
#136
b0 #
0"
#137
b1 $
1"
#138
b1 #
0"
#139
1!
b10 $
1"
#140
b10 #
0"
#141
b11 $
1"
#142
b11 #
0"
#143
0!
b0 $
1"
#144
b0 #
0"
#145
b1 $
1"
#146
b1 #
0"
#147
1!
b10 $
1"
#148
b10 #
0"
#149
b11 $
1"
#150
b11 #
0"
#151
0!
b0 $
1"
#152
b0 #
0"
#153
b1 $
1"
#154
b1 #
0"
#155
1!
b10 $
1"
#156
b10 #
0"
#157
b11 $
1"
#158
b11 #
0"
#159
0!
b0 $
1"
#160
b0 #
0"
#161
b1 $
1"
#162
b1 #
0"
#163
1!
b10 $
1"
#164
b10 #
0"
#165
b11 $
1"
#166
b11 #
0"
#167
0!
b0 $
1"
#168
b0 #
0"
#169
b1 $
1"
#170
b1 #
0"
#171
1!
b10 $
1"
#172
b10 #
0"
#173
b11 $
1"
#174
b11 #
0"
#175
0!
b0 $
1"
#176
b0 #
0"
#177
b1 $
1"
#178
b1 #
0"
#179
1!
b10 $
1"
#180
b10 #
0"
#181
b11 $
1"
#182
b11 #
0"
#183
0!
b0 $
1"
#184
b0 #
0"
#185
b1 $
1"
#186
b1 #
0"
#187
1!
b10 $
1"
#188
b10 #
0"
#189
b11 $
1"
#190
b11 #
0"
#191
0!
b0 $
1"
#192
b0 #
0"
#193
b1 $
1"
#194
b1 #
0"
#195
1!
b10 $
1"
#196
b10 #
0"
#197
b11 $
1"
#198
b11 #
0"
#199
0!
b0 $
1"
