divisor_modificado/baudgen.vh
//-- Fichero baudgen.vh
`define B115200 104
`define B57600  208
`define B38400  313

`define B19200  625
`define B9600   1250
`define B4800   2500
`define B2400   5000
`define B1200   10000
`define B600    20000
`define B300    40000

trasmisor/div.v
`include "baudgen.vh"
module div (clk,clk_ena,clk_out);
  input wire clk;
  input wire clk_ena;
  output wire clk_out;
  parameter M = `B115200;
  localparam  N = $clog2(M);
  reg [N-1:0] cont = 0;

  always @ (posedge clk)
  if (clk_ena == 0)
    cont <= M-1;
  else
    cont <= (cont == M-1)? 0:cont+1;


  //assign clk_out <= cont[N-1]
  assign clk_out = (cont==0) ? clk_ena:0;

endmodule //

trasmisor/tx.v
`include "baudgen.vh"
module tx(clk,dtr,out);
    input wire clk;
    input wire dtr;
    output reg out;
    parameter M = `B115200;
    //localparam  N = $clog2(M);

    reg load;
    reg [9:0] shifter;
    wire clk_baud;

    always @(posedge clk)
      load <= dtr;

    always @(posedge clk)
      if (load == 0)
        shifter <= {"K",2'b01};
      else if (load == 1 && clk_baud == 1)
        shifter <= {1'b1,shifter[9:1]};

    div #(M)
      divisor(
        .clk(clk),
        .clk_ena(load),
        .clk_out(clk_baud)
        );

    always @(posedge clk)
      if (load == 1)
        out <= shifter[0];
      else
        out <= 1'b1;


endmodule //

trasmisor/tx_tb.v
//-- Fichero txtest.v
`include "baudgen.vh"

module tx_tb();

//-- Baudios con los que realizar la simulacion
//-- A 300 baudios, la simulacion tarda mas en realizarse porque los
//-- tiempos son mas largos. A 115200 baudios la simulacion es mucho
//-- mas rapida
localparam M = `B115200;

//-- Tics de reloj para envio de datos a esa velocidad
//-- Se multiplica por 2 porque el periodo del reloj es de 2 unidades
localparam BITRATE = (M << 1);

//-- Tics necesarios para enviar una trama serie completa, mas un bit adicional
localparam FRAME = (BITRATE * 11);

//-- Tiempo entre dos bits enviados
localparam FRAME_WAIT = (BITRATE * 4);

//-- Registro para generar la señal de reloj
reg clk = 0;

//-- Linea de tranmision
wire out;

//-- Simulacion de la señal dtr
reg dtr = 0;

//-- Instanciar el componente
tx #(.M(M))
  dut(
    .clk(clk),
    .dtr(dtr),
    .out(out)
  );

//-- Generador de reloj. Periodo 2 unidades
always
  # 1 clk <= ~clk;

//-- Proceso al inicio
initial begin

  //-- Fichero donde almacenar los resultados
  $dumpfile("tx_tb.vcd");
  $dumpvars(0, tx_tb);

  #1 dtr <= 0;

  //-- Enviar primer caracter
  #FRAME_WAIT dtr <= 1;
  #FRAME dtr <=0;

  //-- Segundo envio
  #FRAME_WAIT dtr <=1;
  #FRAME dtr <=0;

  #FRAME_WAIT $display("FIN de la simulacion");
  $finish;
end

endmodule

trasmisor/tx_tb.vcd
$date
	Sun Oct  6 23:33:41 2019
$end
$version
	Icarus Verilog
$end
$timescale
	1s
$end
$scope module tx_tb $end
$var wire 1 ! out $end
$var reg 1 " clk $end
$var reg 1 # dtr $end
$scope module dut $end
$var wire 1 " clk $end
$var wire 1 # dtr $end
$var wire 1 $ clk_baud $end
$var reg 1 % load $end
$var reg 1 ! out $end
$var reg 10 & shifter [9:0] $end
$scope module divisor $end
$var wire 1 " clk $end
$var wire 1 % clk_ena $end
$var wire 1 $ clk_out $end
$var reg 7 ' cont [6:0] $end
$upscope $end
$upscope $end
$upscope $end
$enddefinitions $end
#0
$dumpvars
b0 '
bx &
x%
x$
0#
0"
x!
$end
#1
0$
b1 '
0%
1!
1"
#2
0"
#3
b100101101 &
b1100111 '
1"
#4
0"
#5
1"
#6
0"
#7
1"
#8
0"
#9
1"
#10
0"
#11
1"
#12
0"
#13
1"
#14
0"
#15
1"
#16
0"
#17
1"
#18
0"
#19
1"
#20
0"
#21
1"
#22
0"
#23
1"
#24
0"
#25
1"
#26
0"
#27
1"
#28
0"
#29
1"
#30
0"
#31
1"
#32
0"
#33
1"
#34
0"
#35
1"
#36
0"
#37
1"
#38
0"
#39
1"
#40
0"
#41
1"
#42
0"
#43
1"
#44
0"
#45
1"
#46
0"
#47
1"
#48
0"
#49
1"
#50
0"
#51
1"
#52
0"
#53
1"
#54
0"
#55
1"
#56
0"
#57
1"
#58
0"
#59
1"
#60
0"
#61
1"
#62
0"
#63
1"
#64
0"
#65
1"
#66
0"
#67
1"
#68
0"
#69
1"
#70
0"
#71
1"
#72
0"
#73
1"
#74
0"
#75
1"
#76
0"
#77
1"
#78
0"
#79
1"
#80
0"
#81
1"
#82
0"
#83
1"
#84
0"
#85
1"
#86
0"
#87
1"
#88
0"
#89
1"
#90
0"
#91
1"
#92
0"
#93
1"
#94
0"
#95
1"
#96
0"
#97
1"
#98
0"
#99
1"
#100
0"
#101
1"
#102
0"
#103
1"
#104
0"
#105
1"
#106
0"
#107
1"
#108
0"
#109
1"
#110
0"
#111
1"
#112
0"
#113
1"
#114
0"
#115
1"
#116
0"
#117
1"
#118
0"
#119
1"
#120
0"
#121
1"
#122
0"
#123
1"
#124
0"
#125
1"
#126
0"
#127
1"
#128
0"
#129
1"
#130
0"
#131
1"
#132
0"
#133
1"
#134
0"
#135
1"
#136
0"
#137
1"
#138
0"
#139
1"
#140
0"
#141
1"
#142
0"
#143
1"
#144
0"
#145
1"
#146
0"
#147
1"
#148
0"
#149
1"
#150
0"
#151
1"
#152
0"
#153
1"
#154
0"
#155
1"
#156
0"
#157
1"
#158
0"
#159
1"
#160
0"
#161
1"
#162
0"
#163
1"
#164
0"
#165
1"
#166
0"
#167
1"
#168
0"
#169
1"
#170
0"
#171
1"
#172
0"
#173
1"
#174
0"
#175
1"
#176
0"
#177
1"
#178
0"
#179
1"
#180
0"
#181
1"
#182
0"
#183
1"
#184
0"
#185
1"
#186
0"
#187
1"
#188
0"
#189
1"
#190
0"
#191
1"
#192
0"
#193
1"
#194
0"
#195
1"
#196
0"
#197
1"
#198
0"
#199
1"
#200
0"
#201
1"
#202
0"
#203
1"
#204
0"
#205
1"
#206
0"
#207
1"
#208
0"
#209
1"
#210
0"
#211
1"
#212
0"
#213
1"
#214
0"
#215
1"
#216
0"
#217
1"
#218
0"
#219
1"
#220
0"
#221
1"
#222
0"
#223
1"
#224
0"
#225
1"
#226
0"
#227
1"
#228
0"
#229
1"
#230
0"
#231
1"
#232
0"
#233
1"
#234
0"
#235
1"
#236
0"
#237
1"
#238
0"
#239
1"
#240
0"
#241
1"
#242
0"
#243
1"
#244
0"
#245
1"
#246
0"
#247
1"
#248
0"
#249
1"
#250
0"
#251
1"
#252
0"
#253
1"
#254
0"
#255
1"
#256
0"
#257
1"
#258
0"
#259
1"
#260
0"
#261
1"
#262
0"
#263
1"
#264
0"
#265
1"
#266
0"
#267
1"
#268
0"
#269
1"
#270
0"
#271
1"
#272
0"
#273
1"
#274
0"
#275
1"
#276
0"
#277
1"
#278
0"
#279
1"
#280
0"
#281
1"
#282
0"
#283
1"
#284
0"
#285
1"
#286
0"
#287
1"
#288
0"
#289
1"
#290
0"
#291
1"
#292
0"
#293
1"
#294
0"
#295
1"
#296
0"
#297
1"
#298
0"
#299
1"
#300
0"
#301
1"
#302
0"
#303
1"
#304
0"
#305
1"
#306
0"
#307
1"
#308
0"
#309
1"
#310
0"
#311
1"
#312
0"
#313
1"
#314
0"
#315
1"
#316
0"
#317
1"
#318
0"
#319
1"
#320
0"
#321
1"
#322
0"
#323
1"
#324
0"
#325
1"
#326
0"
#327
1"
#328
0"
#329
1"
#330
0"
#331
1"
#332
0"
#333
1"
#334
0"
#335
1"
#336
0"
#337
1"
#338
0"
#339
1"
#340
0"
#341
1"
#342
0"
#343
1"
#344
0"
#345
1"
#346
0"
#347
1"
#348
0"
#349
1"
#350
0"
#351
1"
#352
0"
#353
1"
#354
0"
#355
1"
#356
0"
#357
1"
#358
0"
#359
1"
#360
0"
#361
1"
#362
0"
#363
1"
#364
0"
#365
1"
#366
0"
#367
1"
#368
0"
#369
1"
#370
0"
#371
1"
#372
0"
#373
1"
#374
0"
#375
1"
#376
0"
#377
1"
#378
0"
#379
1"
#380
0"
#381
1"
#382
0"
#383
1"
#384
0"
#385
1"
#386
0"
#387
1"
#388
0"
#389
1"
#390
0"
#391
1"
#392
0"
#393
1"
#394
0"
#395
1"
#396
0"
#397
1"
#398
0"
#399
1"
#400
0"
#401
1"
#402
0"
#403
1"
#404
0"
#405
1"
#406
0"
#407
1"
#408
0"
#409
1"
#410
0"
#411
1"
#412
0"
#413
1"
#414
0"
#415
1"
#416
0"
#417
1"
#418
0"
#419
1"
#420
0"
#421
1"
#422
0"
#423
1"
#424
0"
#425
1"
#426
0"
#427
1"
#428
0"
#429
1"
#430
0"
#431
1"
#432
0"
#433
1"
#434
0"
#435
1"
#436
0"
#437
1"
#438
0"
#439
1"
#440
0"
#441
1"
#442
0"
#443
1"
#444
0"
#445
1"
#446
0"
#447
1"
#448
0"
#449
1"
#450
0"
#451
1"
#452
0"
#453
1"
#454
0"
#455
1"
#456
0"
#457
1"
#458
0"
#459
1"
#460
0"
#461
1"
#462
0"
#463
1"
#464
0"
#465
1"
#466
0"
#467
1"
#468
0"
#469
1"
#470
0"
#471
1"
#472
0"
#473
1"
#474
0"
#475
1"
#476
0"
#477
1"
#478
0"
#479
1"
#480
0"
#481
1"
#482
0"
#483
1"
#484
0"
#485
1"
#486
0"
#487
1"
#488
0"
#489
1"
#490
0"
#491
1"
#492
0"
#493
1"
#494
0"
#495
1"
#496
0"
#497
1"
#498
0"
#499
1"
#500
0"
#501
1"
#502
0"
#503
1"
#504
0"
#505
1"
#506
0"
#507
1"
#508
0"
#509
1"
#510
0"
#511
1"
#512
0"
#513
1"
#514
0"
#515
1"
#516
0"
#517
1"
#518
0"
#519
1"
#520
0"
#521
1"
#522
0"
#523
1"
#524
0"
#525
1"
#526
0"
#527
1"
#528
0"
#529
1"
#530
0"
#531
1"
#532
0"
#533
1"
#534
0"
#535
1"
#536
0"
#537
1"
#538
0"
#539
1"
#540
0"
#541
1"
#542
0"
#543
1"
#544
0"
#545
1"
#546
0"
#547
1"
#548
0"
#549
1"
#550
0"
#551
1"
#552
0"
#553
1"
#554
0"
#555
1"
#556
0"
#557
1"
#558
0"
#559
1"
#560
0"
#561
1"
#562
0"
#563
1"
#564
0"
#565
1"
#566
0"
#567
1"
#568
0"
#569
1"
#570
0"
#571
1"
#572
0"
#573
1"
#574
0"
#575
1"
#576
0"
#577
1"
#578
0"
#579
1"
#580
0"
#581
1"
#582
0"
#583
1"
#584
0"
#585
1"
#586
0"
#587
1"
#588
0"
#589
1"
#590
0"
#591
1"
#592
0"
#593
1"
#594
0"
#595
1"
#596
0"
#597
1"
#598
0"
#599
1"
#600
0"
#601
1"
#602
0"
#603
1"
#604
0"
#605
1"
#606
0"
#607
1"
#608
0"
#609
1"
#610
0"
#611
1"
#612
0"
#613
1"
#614
0"
#615
1"
#616
0"
#617
1"
#618
0"
#619
1"
#620
0"
#621
1"
#622
0"
#623
1"
#624
0"
#625
1"
#626
0"
#627
1"
#628
0"
#629
1"
#630
0"
#631
1"
#632
0"
#633
1"
#634
0"
#635
1"
#636
0"
#637
1"
#638
0"
#639
1"
#640
0"
#641
1"
#642
0"
#643
1"
#644
0"
#645
1"
#646
0"
#647
1"
#648
0"
#649
1"
#650
0"
#651
1"
#652
0"
#653
1"
#654
0"
#655
1"
#656
0"
#657
1"
#658
0"
#659
1"
#660
0"
#661
1"
#662
0"
#663
1"
#664
0"
#665
1"
#666
0"
#667
1"
#668
0"
#669
1"
#670
0"
#671
1"
#672
0"
#673
1"
#674
0"
#675
1"
#676
0"
#677
1"
#678
0"
#679
1"
#680
0"
#681
1"
#682
0"
#683
1"
#684
0"
#685
1"
#686
0"
#687
1"
#688
0"
#689
1"
#690
0"
#691
1"
#692
0"
#693
1"
#694
0"
#695
1"
#696
0"
#697
1"
#698
0"
#699
1"
#700
0"
#701
1"
#702
0"
#703
1"
#704
0"
#705
1"
#706
0"
#707
1"
#708
0"
#709
1"
#710
0"
#711
1"
#712
0"
#713
1"
#714
0"
#715
1"
#716
0"
#717
1"
#718
0"
#719
1"
#720
0"
#721
1"
#722
0"
#723
1"
#724
0"
#725
1"
#726
0"
#727
1"
#728
0"
#729
1"
#730
0"
#731
1"
#732
0"
#733
1"
#734
0"
#735
1"
#736
0"
#737
1"
#738
0"
#739
1"
#740
0"
#741
1"
#742
0"
#743
1"
#744
0"
#745
1"
#746
0"
#747
1"
#748
0"
#749
1"
#750
0"
#751
1"
#752
0"
#753
1"
#754
0"
#755
1"
#756
0"
#757
1"
#758
0"
#759
1"
#760
0"
#761
1"
#762
0"
#763
1"
#764
0"
#765
1"
#766
0"
#767
1"
#768
0"
#769
1"
#770
0"
#771
1"
#772
0"
#773
1"
#774
0"
#775
1"
#776
0"
#777
1"
#778
0"
#779
1"
#780
0"
#781
1"
#782
0"
#783
1"
#784
0"
#785
1"
#786
0"
#787
1"
#788
0"
#789
1"
#790
0"
#791
1"
#792
0"
#793
1"
#794
0"
#795
1"
#796
0"
#797
1"
#798
0"
#799
1"
#800
0"
#801
1"
#802
0"
#803
1"
#804
0"
#805
1"
#806
0"
#807
1"
#808
0"
#809
1"
#810
0"
#811
1"
#812
0"
#813
1"
#814
0"
#815
1"
#816
0"
#817
1"
#818
0"
#819
1"
#820
0"
#821
1"
#822
0"
#823
1"
#824
0"
#825
1"
#826
0"
#827
1"
#828
0"
#829
1"
#830
0"
#831
1"
#832
0"
#833
1%
1"
1#
#834
0"
#835
1$
b0 '
1"
#836
0"
#837
0$
b1 '
b1010010110 &
1"
#838
0"
#839
0!
b10 '
1"
#840
0"
#841
b11 '
1"
#842
0"
#843
b100 '
1"
#844
0"
#845
b101 '
1"
#846
0"
#847
b110 '
1"
#848
0"
#849
b111 '
1"
#850
0"
#851
b1000 '
1"
#852
0"
#853
b1001 '
1"
#854
0"
#855
b1010 '
1"
#856
0"
#857
b1011 '
1"
#858
0"
#859
b1100 '
1"
#860
0"
#861
b1101 '
1"
#862
0"
#863
b1110 '
1"
#864
0"
#865
b1111 '
1"
#866
0"
#867
b10000 '
1"
#868
0"
#869
b10001 '
1"
#870
0"
#871
b10010 '
1"
#872
0"
#873
b10011 '
1"
#874
0"
#875
b10100 '
1"
#876
0"
#877
b10101 '
1"
#878
0"
#879
b10110 '
1"
#880
0"
#881
b10111 '
1"
#882
0"
#883
b11000 '
1"
#884
0"
#885
b11001 '
1"
#886
0"
#887
b11010 '
1"
#888
0"
#889
b11011 '
1"
#890
0"
#891
b11100 '
1"
#892
0"
#893
b11101 '
1"
#894
0"
#895
b11110 '
1"
#896
0"
#897
b11111 '
1"
#898
0"
#899
b100000 '
1"
#900
0"
#901
b100001 '
1"
#902
0"
#903
b100010 '
1"
#904
0"
#905
b100011 '
1"
#906
0"
#907
b100100 '
1"
#908
0"
#909
b100101 '
1"
#910
0"
#911
b100110 '
1"
#912
0"
#913
b100111 '
1"
#914
0"
#915
b101000 '
1"
#916
0"
#917
b101001 '
1"
#918
0"
#919
b101010 '
1"
#920
0"
#921
b101011 '
1"
#922
0"
#923
b101100 '
1"
#924
0"
#925
b101101 '
1"
#926
0"
#927
b101110 '
1"
#928
0"
#929
b101111 '
1"
#930
0"
#931
b110000 '
1"
#932
0"
#933
b110001 '
1"
#934
0"
#935
b110010 '
1"
#936
0"
#937
b110011 '
1"
#938
0"
#939
b110100 '
1"
#940
0"
#941
b110101 '
1"
#942
0"
#943
b110110 '
1"
#944
0"
#945
b110111 '
1"
#946
0"
#947
b111000 '
1"
#948
0"
#949
b111001 '
1"
#950
0"
#951
b111010 '
1"
#952
0"
#953
b111011 '
1"
#954
0"
#955
b111100 '
1"
#956
0"
#957
b111101 '
1"
#958
0"
#959
b111110 '
1"
#960
0"
#961
b111111 '
1"
#962
0"
#963
b1000000 '
1"
#964
0"
#965
b1000001 '
1"
#966
0"
#967
b1000010 '
1"
#968
0"
#969
b1000011 '
1"
#970
0"
#971
b1000100 '
1"
#972
0"
#973
b1000101 '
1"
#974
0"
#975
b1000110 '
1"
#976
0"
#977
b1000111 '
1"
#978
0"
#979
b1001000 '
1"
#980
0"
#981
b1001001 '
1"
#982
0"
#983
b1001010 '
1"
#984
0"
#985
b1001011 '
1"
#986
0"
#987
b1001100 '
1"
#988
0"
#989
b1001101 '
1"
#990
0"
#991
b1001110 '
1"
#992
0"
#993
b1001111 '
1"
#994
0"
#995
b1010000 '
1"
#996
0"
#997
b1010001 '
1"
#998
0"
#999
b1010010 '
1"
#1000
0"
#1001
b1010011 '
1"
#1002
0"
#1003
b1010100 '
1"
#1004
0"
#1005
b1010101 '
1"
#1006
0"
#1007
b1010110 '
1"
#1008
0"
#1009
b1010111 '
1"
#1010
0"
#1011
b1011000 '
1"
#1012
0"
#1013
b1011001 '
1"
#1014
0"
#1015
b1011010 '
1"
#1016
0"
#1017
b1011011 '
1"
#1018
0"
#1019
b1011100 '
1"
#1020
0"
#1021
b1011101 '
1"
#1022
0"
#1023
b1011110 '
1"
#1024
0"
#1025
b1011111 '
1"
#1026
0"
#1027
b1100000 '
1"
#1028
0"
#1029
b1100001 '
1"
#1030
0"
#1031
b1100010 '
1"
#1032
0"
#1033
b1100011 '
1"
#1034
0"
#1035
b1100100 '
1"
#1036
0"
#1037
b1100101 '
1"
#1038
0"
#1039
b1100110 '
1"
#1040
0"
#1041
b1100111 '
1"
#1042
0"
#1043
1$
b0 '
1"
#1044
0"
#1045
0$
b1 '
b1101001011 &
1"
#1046
0"
#1047
1!
b10 '
1"
#1048
0"
#1049
b11 '
1"
#1050
0"
#1051
b100 '
1"
#1052
0"
#1053
b101 '
1"
#1054
0"
#1055
b110 '
1"
#1056
0"
#1057
b111 '
1"
#1058
0"
#1059
b1000 '
1"
#1060
0"
#1061
b1001 '
1"
#1062
0"
#1063
b1010 '
1"
#1064
0"
#1065
b1011 '
1"
#1066
0"
#1067
b1100 '
1"
#1068
0"
#1069
b1101 '
1"
#1070
0"
#1071
b1110 '
1"
#1072
0"
#1073
b1111 '
1"
#1074
0"
#1075
b10000 '
1"
#1076
0"
#1077
b10001 '
1"
#1078
0"
#1079
b10010 '
1"
#1080
0"
#1081
b10011 '
1"
#1082
0"
#1083
b10100 '
1"
#1084
0"
#1085
b10101 '
1"
#1086
0"
#1087
b10110 '
1"
#1088
0"
#1089
b10111 '
1"
#1090
0"
#1091
b11000 '
1"
#1092
0"
#1093
b11001 '
1"
#1094
0"
#1095
b11010 '
1"
#1096
0"
#1097
b11011 '
1"
#1098
0"
#1099
b11100 '
1"
#1100
0"
#1101
b11101 '
1"
#1102
0"
#1103
b11110 '
1"
#1104
0"
#1105
b11111 '
1"
#1106
0"
#1107
b100000 '
1"
#1108
0"
#1109
b100001 '
1"
#1110
0"
#1111
b100010 '
1"
#1112
0"
#1113
b100011 '
1"
#1114
0"
#1115
b100100 '
1"
#1116
0"
#1117
b100101 '
1"
#1118
0"
#1119
b100110 '
1"
#1120
0"
#1121
b100111 '
1"
#1122
0"
#1123
b101000 '
1"
#1124
0"
#1125
b101001 '
1"
#1126
0"
#1127
b101010 '
1"
#1128
0"
#1129
b101011 '
1"
#1130
0"
#1131
b101100 '
1"
#1132
0"
#1133
b101101 '
1"
#1134
0"
#1135
b101110 '
1"
#1136
0"
#1137
b101111 '
1"
#1138
0"
#1139
b110000 '
1"
#1140
0"
#1141
b110001 '
1"
#1142
0"
#1143
b110010 '
1"
#1144
0"
#1145
b110011 '
1"
#1146
0"
#1147
b110100 '
1"
#1148
0"
#1149
b110101 '
1"
#1150
0"
#1151
b110110 '
1"
#1152
0"
#1153
b110111 '
1"
#1154
0"
#1155
b111000 '
1"
#1156
0"
#1157
b111001 '
1"
#1158
0"
#1159
b111010 '
1"
#1160
0"
#1161
b111011 '
1"
#1162
0"
#1163
b111100 '
1"
#1164
0"
#1165
b111101 '
1"
#1166
0"
#1167
b111110 '
1"
#1168
0"
#1169
b111111 '
1"
#1170
0"
#1171
b1000000 '
1"
#1172
0"
#1173
b1000001 '
1"
#1174
0"
#1175
b1000010 '
1"
#1176
0"
#1177
b1000011 '
1"
#1178
0"
#1179
b1000100 '
1"
#1180
0"
#1181
b1000101 '
1"
#1182
0"
#1183
b1000110 '
1"
#1184
0"
#1185
b1000111 '
1"
#1186
0"
#1187
b1001000 '
1"
#1188
0"
#1189
b1001001 '
1"
#1190
0"
#1191
b1001010 '
1"
#1192
0"
#1193
b1001011 '
1"
#1194
0"
#1195
b1001100 '
1"
#1196
0"
#1197
b1001101 '
1"
#1198
0"
#1199
b1001110 '
1"
#1200
0"
#1201
b1001111 '
1"
#1202
0"
#1203
b1010000 '
1"
#1204
0"
#1205
b1010001 '
1"
#1206
0"
#1207
b1010010 '
1"
#1208
0"
#1209
b1010011 '
1"
#1210
0"
#1211
b1010100 '
1"
#1212
0"
#1213
b1010101 '
1"
#1214
0"
#1215
b1010110 '
1"
#1216
0"
#1217
b1010111 '
1"
#1218
0"
#1219
b1011000 '
1"
#1220
0"
#1221
b1011001 '
1"
#1222
0"
#1223
b1011010 '
1"
#1224
0"
#1225
b1011011 '
1"
#1226
0"
#1227
b1011100 '
1"
#1228
0"
#1229
b1011101 '
1"
#1230
0"
#1231
b1011110 '
1"
#1232
0"
#1233
b1011111 '
1"
#1234
0"
#1235
b1100000 '
1"
#1236
0"
#1237
b1100001 '
1"
#1238
0"
#1239
b1100010 '
1"
#1240
0"
#1241
b1100011 '
1"
#1242
0"
#1243
b1100100 '
1"
#1244
0"
#1245
b1100101 '
1"
#1246
0"
#1247
b1100110 '
1"
#1248
0"
#1249
b1100111 '
1"
#1250
0"
#1251
1$
b0 '
1"
#1252
0"
#1253
0$
b1 '
b1110100101 &
1"
#1254
0"
#1255
b10 '
1"
#1256
0"
#1257
b11 '
1"
#1258
0"
#1259
b100 '
1"
#1260
0"
#1261
b101 '
1"
#1262
0"
#1263
b110 '
1"
#1264
0"
#1265
b111 '
1"
#1266
0"
#1267
b1000 '
1"
#1268
0"
#1269
b1001 '
1"
#1270
0"
#1271
b1010 '
1"
#1272
0"
#1273
b1011 '
1"
#1274
0"
#1275
b1100 '
1"
#1276
0"
#1277
b1101 '
1"
#1278
0"
#1279
b1110 '
1"
#1280
0"
#1281
b1111 '
1"
#1282
0"
#1283
b10000 '
1"
#1284
0"
#1285
b10001 '
1"
#1286
0"
#1287
b10010 '
1"
#1288
0"
#1289
b10011 '
1"
#1290
0"
#1291
b10100 '
1"
#1292
0"
#1293
b10101 '
1"
#1294
0"
#1295
b10110 '
1"
#1296
0"
#1297
b10111 '
1"
#1298
0"
#1299
b11000 '
1"
#1300
0"
#1301
b11001 '
1"
#1302
0"
#1303
b11010 '
1"
#1304
0"
#1305
b11011 '
1"
#1306
0"
#1307
b11100 '
1"
#1308
0"
#1309
b11101 '
1"
#1310
0"
#1311
b11110 '
1"
#1312
0"
#1313
b11111 '
1"
#1314
0"
#1315
b100000 '
1"
#1316
0"
#1317
b100001 '
1"
#1318
0"
#1319
b100010 '
1"
#1320
0"
#1321
b100011 '
1"
#1322
0"
#1323
b100100 '
1"
#1324
0"
#1325
b100101 '
1"
#1326
0"
#1327
b100110 '
1"
#1328
0"
#1329
b100111 '
1"
#1330
0"
#1331
b101000 '
1"
#1332
0"
#1333
b101001 '
1"
#1334
0"
#1335
b101010 '
1"
#1336
0"
#1337
b101011 '
1"
#1338
0"
#1339
b101100 '
1"
#1340
0"
#1341
b101101 '
1"
#1342
0"
#1343
b101110 '
1"
#1344
0"
#1345
b101111 '
1"
#1346
0"
#1347
b110000 '
1"
#1348
0"
#1349
b110001 '
1"
#1350
0"
#1351
b110010 '
1"
#1352
0"
#1353
b110011 '
1"
#1354
0"
#1355
b110100 '
1"
#1356
0"
#1357
b110101 '
1"
#1358
0"
#1359
b110110 '
1"
#1360
0"
#1361
b110111 '
1"
#1362
0"
#1363
b111000 '
1"
#1364
0"
#1365
b111001 '
1"
#1366
0"
#1367
b111010 '
1"
#1368
0"
#1369
b111011 '
1"
#1370
0"
#1371
b111100 '
1"
#1372
0"
#1373
b111101 '
1"
#1374
0"
#1375
b111110 '
1"
#1376
0"
#1377
b111111 '
1"
#1378
0"
#1379
b1000000 '
1"
#1380
0"
#1381
b1000001 '
1"
#1382
0"
#1383
b1000010 '
1"
#1384
0"
#1385
b1000011 '
1"
#1386
0"
#1387
b1000100 '
1"
#1388
0"
#1389
b1000101 '
1"
#1390
0"
#1391
b1000110 '
1"
#1392
0"
#1393
b1000111 '
1"
#1394
0"
#1395
b1001000 '
1"
#1396
0"
#1397
b1001001 '
1"
#1398
0"
#1399
b1001010 '
1"
#1400
0"
#1401
b1001011 '
1"
#1402
0"
#1403
b1001100 '
1"
#1404
0"
#1405
b1001101 '
1"
#1406
0"
#1407
b1001110 '
1"
#1408
0"
#1409
b1001111 '
1"
#1410
0"
#1411
b1010000 '
1"
#1412
0"
#1413
b1010001 '
1"
#1414
0"
#1415
b1010010 '
1"
#1416
0"
#1417
b1010011 '
1"
#1418
0"
#1419
b1010100 '
1"
#1420
0"
#1421
b1010101 '
1"
#1422
0"
#1423
b1010110 '
1"
#1424
0"
#1425
b1010111 '
1"
#1426
0"
#1427
b1011000 '
1"
#1428
0"
#1429
b1011001 '
1"
#1430
0"
#1431
b1011010 '
1"
#1432
0"
#1433
b1011011 '
1"
#1434
0"
#1435
b1011100 '
1"
#1436
0"
#1437
b1011101 '
1"
#1438
0"
#1439
b1011110 '
1"
#1440
0"
#1441
b1011111 '
1"
#1442
0"
#1443
b1100000 '
1"
#1444
0"
#1445
b1100001 '
1"
#1446
0"
#1447
b1100010 '
1"
#1448
0"
#1449
b1100011 '
1"
#1450
0"
#1451
b1100100 '
1"
#1452
0"
#1453
b1100101 '
1"
#1454
0"
#1455
b1100110 '
1"
#1456
0"
#1457
b1100111 '
1"
#1458
0"
#1459
1$
b0 '
1"
#1460
0"
#1461
0$
b1 '
b1111010010 &
1"
#1462
0"
#1463
0!
b10 '
1"
#1464
0"
#1465
b11 '
1"
#1466
0"
#1467
b100 '
1"
#1468
0"
#1469
b101 '
1"
#1470
0"
#1471
b110 '
1"
#1472
0"
#1473
b111 '
1"
#1474
0"
#1475
b1000 '
1"
#1476
0"
#1477
b1001 '
1"
#1478
0"
#1479
b1010 '
1"
#1480
0"
#1481
b1011 '
1"
#1482
0"
#1483
b1100 '
1"
#1484
0"
#1485
b1101 '
1"
#1486
0"
#1487
b1110 '
1"
#1488
0"
#1489
b1111 '
1"
#1490
0"
#1491
b10000 '
1"
#1492
0"
#1493
b10001 '
1"
#1494
0"
#1495
b10010 '
1"
#1496
0"
#1497
b10011 '
1"
#1498
0"
#1499
b10100 '
1"
#1500
0"
#1501
b10101 '
1"
#1502
0"
#1503
b10110 '
1"
#1504
0"
#1505
b10111 '
1"
#1506
0"
#1507
b11000 '
1"
#1508
0"
#1509
b11001 '
1"
#1510
0"
#1511
b11010 '
1"
#1512
0"
#1513
b11011 '
1"
#1514
0"
#1515
b11100 '
1"
#1516
0"
#1517
b11101 '
1"
#1518
0"
#1519
b11110 '
1"
#1520
0"
#1521
b11111 '
1"
#1522
0"
#1523
b100000 '
1"
#1524
0"
#1525
b100001 '
1"
#1526
0"
#1527
b100010 '
1"
#1528
0"
#1529
b100011 '
1"
#1530
0"
#1531
b100100 '
1"
#1532
0"
#1533
b100101 '
1"
#1534
0"
#1535
b100110 '
1"
#1536
0"
#1537
b100111 '
1"
#1538
0"
#1539
b101000 '
1"
#1540
0"
#1541
b101001 '
1"
#1542
0"
#1543
b101010 '
1"
#1544
0"
#1545
b101011 '
1"
#1546
0"
#1547
b101100 '
1"
#1548
0"
#1549
b101101 '
1"
#1550
0"
#1551
b101110 '
1"
#1552
0"
#1553
b101111 '
1"
#1554
0"
#1555
b110000 '
1"
#1556
0"
#1557
b110001 '
1"
#1558
0"
#1559
b110010 '
1"
#1560
0"
#1561
b110011 '
1"
#1562
0"
#1563
b110100 '
1"
#1564
0"
#1565
b110101 '
1"
#1566
0"
#1567
b110110 '
1"
#1568
0"
#1569
b110111 '
1"
#1570
0"
#1571
b111000 '
1"
#1572
0"
#1573
b111001 '
1"
#1574
0"
#1575
b111010 '
1"
#1576
0"
#1577
b111011 '
1"
#1578
0"
#1579
b111100 '
1"
#1580
0"
#1581
b111101 '
1"
#1582
0"
#1583
b111110 '
1"
#1584
0"
#1585
b111111 '
1"
#1586
0"
#1587
b1000000 '
1"
#1588
0"
#1589
b1000001 '
1"
#1590
0"
#1591
b1000010 '
1"
#1592
0"
#1593
b1000011 '
1"
#1594
0"
#1595
b1000100 '
1"
#1596
0"
#1597
b1000101 '
1"
#1598
0"
#1599
b1000110 '
1"
#1600
0"
#1601
b1000111 '
1"
#1602
0"
#1603
b1001000 '
1"
#1604
0"
#1605
b1001001 '
1"
#1606
0"
#1607
b1001010 '
1"
#1608
0"
#1609
b1001011 '
1"
#1610
0"
#1611
b1001100 '
1"
#1612
0"
#1613
b1001101 '
1"
#1614
0"
#1615
b1001110 '
1"
#1616
0"
#1617
b1001111 '
1"
#1618
0"
#1619
b1010000 '
1"
#1620
0"
#1621
b1010001 '
1"
#1622
0"
#1623
b1010010 '
1"
#1624
0"
#1625
b1010011 '
1"
#1626
0"
#1627
b1010100 '
1"
#1628
0"
#1629
b1010101 '
1"
#1630
0"
#1631
b1010110 '
1"
#1632
0"
#1633
b1010111 '
1"
#1634
0"
#1635
b1011000 '
1"
#1636
0"
#1637
b1011001 '
1"
#1638
0"
#1639
b1011010 '
1"
#1640
0"
#1641
b1011011 '
1"
#1642
0"
#1643
b1011100 '
1"
#1644
0"
#1645
b1011101 '
1"
#1646
0"
#1647
b1011110 '
1"
#1648
0"
#1649
b1011111 '
1"
#1650
0"
#1651
b1100000 '
1"
#1652
0"
#1653
b1100001 '
1"
#1654
0"
#1655
b1100010 '
1"
#1656
0"
