_cont_seg/divider.vh
//-- Megaherzios  MHz
`define F_4MHz 3
`define F_3MHz 4
`define F_2MHz 6
`define F_1MHz 12

//-- Kilohercios KHz
`define F_4KHz 3000
`define F_3KHz 4000
`define F_2KHz 6000
`define F_1KHz 12000

//-- Hertzios (Hz)
`define F_4Hz   3000000
`define F_3Hz   4000000
`define F_2Hz   6000000
`define F_1Hz   12000000

_divisorM/div.v
module div(clk_i, clk_o);
  input wire clk_i;
  output wire clk_o;

  parameter M = 12_000_000;
  localparam N = $clog2(M);

  reg [N-1:0] cont = 0;

  always @ (posedge clk_i)
    if (cont == M-1)
      cont <= 0;
    else
      cont <= cont + 1;

  assign clk_o = cont[N-1];

endmodule //

_cont_seg/cont1s.v
`include "divider.vh"

module cont1s(data,clk);
  output wire [3:0] data;
  input wire clk;
  wire clk_1s;
  reg [3:0] dout = 0;

  parameter M = `F_1Hz;
  //parameter M = 12000000;

  div #(M)
    DIV(
      .clk_i(clk),
      .clk_o(clk_1s)
      );

  always @ (posedge clk_1s)
    if (dout == 16)
      dout <= 0;
    else
      dout <= dout + 1;

  assign data = dout;

endmodule //

_cont_seg/cont1s_tb.v
module cont1s_tb();
  wire [3:0] data;
  reg clk = 0;

  cont1s #(5)
    CONT(
      .clk(clk),
      .data(data)
      );

  always #1 clk = ~clk;

  initial begin
    $dumpfile("cont1s_tb.vcd");
    $dumpvars(0,cont1s_tb);
    #300 $display("FIN");
    $finish;
  end

endmodule //

_cont_seg/cont1s_tb.vcd
$date
	Sat Sep 21 18:03:59 2019
$end
$version
	Icarus Verilog
$end
$timescale
	1s
$end
$scope module cont1s_tb $end
$var wire 4 ! data [3:0] $end
$var reg 1 " clk $end
$scope module CONT $end
$var wire 1 " clk $end
$var wire 4 # data [3:0] $end
$var wire 1 $ clk_1s $end
$var reg 4 % dout [3:0] $end
$scope module DIV $end
$var wire 1 " clk_i $end
$var wire 1 $ clk_o $end
$var reg 3 & cont [2:0] $end
$upscope $end
$upscope $end
$upscope $end
$enddefinitions $end
#0
$dumpvars
b0 &
b0 %
0$
b0 #
0"
b0 !
$end
#1
b1 &
1"
#2
0"
#3
b10 &
1"
#4
0"
#5
b11 &
1"
#6
0"
#7
b1 !
b1 #
b1 %
1$
b100 &
1"
#8
0"
#9
0$
b0 &
1"
#10
0"
#11
b1 &
1"
#12
0"
#13
b10 &
1"
#14
0"
#15
b11 &
1"
#16
0"
#17
b10 !
b10 #
b10 %
1$
b100 &
1"
#18
0"
#19
0$
b0 &
1"
#20
0"
#21
b1 &
1"
#22
0"
#23
b10 &
1"
#24
0"
#25
b11 &
1"
#26
0"
#27
b11 !
b11 #
b11 %
1$
b100 &
1"
#28
0"
#29
0$
b0 &
1"
#30
0"
#31
b1 &
1"
#32
0"
#33
b10 &
1"
#34
0"
#35
b11 &
1"
#36
0"
#37
b100 !
b100 #
b100 %
1$
b100 &
1"
#38
0"
#39
0$
b0 &
1"
#40
0"
#41
b1 &
1"
#42
0"
#43
b10 &
1"
#44
0"
#45
b11 &
1"
#46
0"
#47
b101 !
b101 #
b101 %
1$
b100 &
1"
#48
0"
#49
0$
b0 &
1"
#50
0"
#51
b1 &
1"
#52
0"
#53
b10 &
1"
#54
0"
#55
b11 &
1"
#56
0"
#57
b110 !
b110 #
b110 %
1$
b100 &
1"
#58
0"
#59
0$
b0 &
1"
#60
0"
#61
b1 &
1"
#62
0"
#63
b10 &
1"
#64
0"
#65
b11 &
1"
#66
0"
#67
b111 !
b111 #
b111 %
1$
b100 &
1"
#68
0"
#69
0$
b0 &
1"
#70
0"
#71
b1 &
1"
#72
0"
#73
b10 &
1"
#74
0"
#75
b11 &
1"
#76
0"
#77
b1000 !
b1000 #
b1000 %
1$
b100 &
1"
#78
0"
#79
0$
b0 &
1"
#80
0"
#81
b1 &
1"
#82
0"
#83
b10 &
1"
#84
0"
#85
b11 &
1"
#86
0"
#87
b1001 !
b1001 #
b1001 %
1$
b100 &
1"
#88
0"
#89
0$
b0 &
1"
#90
0"
#91
b1 &
1"
#92
0"
#93
b10 &
1"
#94
0"
#95
b11 &
1"
#96
0"
#97
b1010 !
b1010 #
b1010 %
1$
b100 &
1"
#98
0"
#99
0$
b0 &
1"
#100
0"
#101
b1 &
1"
#102
0"
#103
b10 &
1"
#104
0"
#105
b11 &
1"
#106
0"
#107
b1011 !
b1011 #
b1011 %
1$
b100 &
1"
#108
0"
#109
0$
b0 &
1"
#110
0"
#111
b1 &
1"
#112
0"
#113
b10 &
1"
#114
0"
#115
b11 &
1"
#116
0"
#117
b1100 !
b1100 #
b1100 %
1$
b100 &
1"
#118
0"
#119
0$
b0 &
1"
#120
0"
#121
b1 &
1"
#122
0"
#123
b10 &
1"
#124
0"
#125
b11 &
1"
#126
0"
#127
b1101 !
b1101 #
b1101 %
1$
b100 &
1"
#128
0"
#129
0$
b0 &
1"
#130
0"
#131
b1 &
1"
#132
0"
#133
b10 &
1"
#134
0"
#135
b11 &
1"
#136
0"
#137
b1110 !
b1110 #
b1110 %
1$
b100 &
1"
#138
0"
#139
0$
b0 &
1"
#140
0"
#141
b1 &
1"
#142
0"
#143
b10 &
1"
#144
0"
#145
b11 &
1"
#146
0"
#147
b1111 !
b1111 #
b1111 %
1$
b100 &
1"
#148
0"
#149
0$
b0 &
1"
#150
0"
#151
b1 &
1"
#152
0"
#153
b10 &
1"
#154
0"
#155
b11 &
1"
#156
0"
#157
b0 !
b0 #
b0 %
1$
b100 &
1"
#158
0"
#159
0$
b0 &
1"
#160
0"
#161
b1 &
1"
#162
0"
#163
b10 &
1"
#164
0"
#165
b11 &
1"
#166
0"
#167
b1 !
b1 #
b1 %
1$
b100 &
1"
#168
0"
#169
0$
b0 &
1"
#170
0"
#171
b1 &
1"
#172
0"
#173
b10 &
1"
#174
0"
#175
b11 &
1"
#176
0"
#177
b10 !
b10 #
b10 %
1$
b100 &
1"
#178
0"
#179
0$
b0 &
1"
#180
0"
#181
b1 &
1"
#182
0"
#183
b10 &
1"
#184
0"
#185
b11 &
1"
#186
0"
#187
b11 !
b11 #
b11 %
1$
b100 &
1"
#188
0"
#189
0$
b0 &
1"
#190
0"
#191
b1 &
1"
#192
0"
#193
b10 &
1"
#194
0"
#195
b11 &
1"
#196
0"
#197
b100 !
b100 #
b100 %
1$
b100 &
1"
#198
0"
#199
0$
b0 &
1"
#200
0"
#201
b1 &
1"
#202
0"
#203
b10 &
1"
#204
0"
#205
b11 &
1"
#206
0"
#207
b101 !
b101 #
b101 %
1$
b100 &
1"
#208
0"
#209
0$
b0 &
1"
#210
0"
#211
b1 &
1"
#212
0"
#213
b10 &
1"
#214
0"
#215
b11 &
1"
#216
0"
#217
b110 !
b110 #
b110 %
1$
b100 &
1"
#218
0"
#219
0$
b0 &
1"
#220
0"
#221
b1 &
1"
#222
0"
#223
b10 &
1"
#224
0"
#225
b11 &
1"
#226
0"
#227
b111 !
b111 #
b111 %
1$
b100 &
1"
#228
0"
#229
0$
b0 &
1"
#230
0"
#231
b1 &
1"
#232
0"
#233
b10 &
1"
#234
0"
#235
b11 &
1"
#236
0"
#237
b1000 !
b1000 #
b1000 %
1$
b100 &
1"
#238
0"
#239
0$
b0 &
1"
#240
0"
#241
b1 &
1"
#242
0"
#243
b10 &
1"
#244
0"
#245
b11 &
1"
#246
0"
#247
b1001 !
b1001 #
b1001 %
1$
b100 &
1"
#248
0"
#249
0$
b0 &
1"
#250
0"
#251
b1 &
1"
#252
0"
#253
b10 &
1"
#254
0"
#255
b11 &
1"
#256
0"
#257
b1010 !
b1010 #
b1010 %
1$
b100 &
1"
#258
0"
#259
0$
b0 &
1"
#260
0"
#261
b1 &
1"
#262
0"
#263
b10 &
1"
#264
0"
#265
b11 &
1"
#266
0"
#267
b1011 !
b1011 #
b1011 %
1$
b100 &
1"
#268
0"
#269
0$
b0 &
1"
#270
0"
#271
b1 &
1"
#272
0"
#273
b10 &
1"
#274
0"
#275
b11 &
1"
#276
0"
#277
b1100 !
b1100 #
b1100 %
1$
b100 &
1"
#278
0"
#279
0$
b0 &
1"
#280
0"
#281
b1 &
1"
#282
0"
#283
b10 &
1"
#284
0"
#285
b11 &
1"
#286
0"
#287
b1101 !
b1101 #
b1101 %
1$
b100 &
1"
#288
0"
#289
0$
b0 &
1"
#290
0"
#291
b1 &
1"
#292
0"
#293
b10 &
1"
#294
0"
#295
b11 &
1"
#296
0"
#297
b1110 !
b1110 #
b1110 %
1$
b100 &
1"
#298
0"
#299
0$
b0 &
1"
