cont_modulo3/count.v
// Solo Simulacion
module count(data,clk);
  output reg [1:0] data = 0;
  input clk;

  always @ (posedge clk)
    if (data == 2)
      data <= 0;
    else
      data <= data + 1;

endmodule //

cont_modulo3/count_tb.v
module count_tb();
  reg clk = 0;
  wire [1:0] data;

  count
    CONT(
      .clk(clk),
      .data(data)
      );

  always #1 clk = ~clk;

  initial begin
    $dumpfile("count_tb.vcd");
    $dumpvars(0, count_tb);
    #50 $display("Fin");
    $finish;
  end

endmodule //

cont_modulo3/count_tb.vcd
$date
	Sat Sep 21 14:47:19 2019
$end
$version
	Icarus Verilog
$end
$timescale
	1s
$end
$scope module count_tb $end
$var wire 2 ! data [1:0] $end
$var reg 1 " clk $end
$scope module CONT $end
$var wire 1 " clk $end
$var reg 2 # data [1:0] $end
$upscope $end
$upscope $end
$enddefinitions $end
#0
$dumpvars
b0 #
0"
b0 !
$end
#1
b1 !
b1 #
1"
#2
0"
#3
b10 !
b10 #
1"
#4
0"
#5
b0 !
b0 #
1"
#6
0"
#7
b1 !
b1 #
1"
#8
0"
#9
b10 !
b10 #
1"
#10
0"
#11
b0 !
b0 #
1"
#12
0"
#13
b1 !
b1 #
1"
#14
0"
#15
b10 !
b10 #
1"
#16
0"
#17
b0 !
b0 #
1"
#18
0"
#19
b1 !
b1 #
1"
#20
0"
#21
b10 !
b10 #
1"
#22
0"
#23
b0 !
b0 #
1"
#24
0"
#25
b1 !
b1 #
1"
#26
0"
#27
b10 !
b10 #
1"
#28
0"
#29
b0 !
b0 #
1"
#30
0"
#31
b1 !
b1 #
1"
#32
0"
#33
b10 !
b10 #
1"
#34
0"
#35
b0 !
b0 #
1"
#36
0"
#37
b1 !
b1 #
1"
#38
0"
#39
b10 !
b10 #
1"
#40
0"
#41
b0 !
b0 #
1"
#42
0"
#43
b1 !
b1 #
1"
#44
0"
#45
b10 !
b10 #
1"
#46
0"
#47
b0 !
b0 #
1"
#48
0"
#49
b1 !
b1 #
1"
