divisor_modificado/baudgen.vh
//-- Fichero baudgen.vh
`define B115200 104
`define B57600  208
`define B38400  313

`define B19200  625
`define B9600   1250
`define B4800   2500
`define B2400   5000
`define B1200   10000
`define B600    20000
`define B300    40000

trasmisor/div.v
`include "baudgen.vh"
module div (clk,clk_ena,clk_out);
  input wire clk;
  input wire clk_ena;
  output wire clk_out;
  parameter M = `B115200;
  localparam  N = $clog2(M);
  reg [N-1:0] cont = 0;

  always @ (posedge clk)
  if (clk_ena == 0)
    cont <= M-1;
  else
    cont <= (cont == M-1)? 0:cont+1;


  //assign clk_out <= cont[N-1]
  assign clk_out = (cont==0) ? clk_ena:0;

endmodule //

divisor_modificado/div_tb.v
`include "baudgen.vh"
module div_tb();
  reg clk = 0;
  reg clk_ena = 0;
  wire clk_out;
  parameter M0 = `B115200;
  div #(.N($clog2(M0)),.M(M0))
    dut(
      .clk(clk),
      .clk_ena(clk_ena),
      .clk_out(clk_out)
      );


always #1 clk <= ~clk;
initial begin
  $dumpfile("div_tb.vcd");
  $dumpvars(0,div_tb);
  #10 clk_ena <= 1;
  #200 clk_ena <= 0;
  #400$display("FIN");
  $finish;
end
endmodule

divisor_modificado/div_tb.vcd
$date
	Sun Oct  6 19:25:13 2019
$end
$version
	Icarus Verilog
$end
$timescale
	1s
$end
$scope module div_tb $end
$var wire 1 ! clk_out $end
$var reg 1 " clk $end
$var reg 1 # clk_ena $end
$scope module dut $end
$var wire 1 " clk $end
$var wire 1 # clk_ena $end
$var wire 1 ! clk_out $end
$var reg 7 $ cont [6:0] $end
$upscope $end
$upscope $end
$enddefinitions $end
#0
$dumpvars
b0 $
0#
0"
0!
$end
#1
b1100111 $
1"
#2
0"
#3
1"
#4
0"
#5
1"
#6
0"
#7
1"
#8
0"
#9
1"
#10
0"
1#
#11
1!
b0 $
1"
#12
0"
#13
0!
b1 $
1"
#14
0"
#15
b10 $
1"
#16
0"
#17
b11 $
1"
#18
0"
#19
b100 $
1"
#20
0"
#21
b101 $
1"
#22
0"
#23
b110 $
1"
#24
0"
#25
b111 $
1"
#26
0"
#27
b1000 $
1"
#28
0"
#29
b1001 $
1"
#30
0"
#31
b1010 $
1"
#32
0"
#33
b1011 $
1"
#34
0"
#35
b1100 $
1"
#36
0"
#37
b1101 $
1"
#38
0"
#39
b1110 $
1"
#40
0"
#41
b1111 $
1"
#42
0"
#43
b10000 $
1"
#44
0"
#45
b10001 $
1"
#46
0"
#47
b10010 $
1"
#48
0"
#49
b10011 $
1"
#50
0"
#51
b10100 $
1"
#52
0"
#53
b10101 $
1"
#54
0"
#55
b10110 $
1"
#56
0"
#57
b10111 $
1"
#58
0"
#59
b11000 $
1"
#60
0"
#61
b11001 $
1"
#62
0"
#63
b11010 $
1"
#64
0"
#65
b11011 $
1"
#66
0"
#67
b11100 $
1"
#68
0"
#69
b11101 $
1"
#70
0"
#71
b11110 $
1"
#72
0"
#73
b11111 $
1"
#74
0"
#75
b100000 $
1"
#76
0"
#77
b100001 $
1"
#78
0"
#79
b100010 $
1"
#80
0"
#81
b100011 $
1"
#82
0"
#83
b100100 $
1"
#84
0"
#85
b100101 $
1"
#86
0"
#87
b100110 $
1"
#88
0"
#89
b100111 $
1"
#90
0"
#91
b101000 $
1"
#92
0"
#93
b101001 $
1"
#94
0"
#95
b101010 $
1"
#96
0"
#97
b101011 $
1"
#98
0"
#99
b101100 $
1"
#100
0"
#101
b101101 $
1"
#102
0"
#103
b101110 $
1"
#104
0"
#105
b101111 $
1"
#106
0"
#107
b110000 $
1"
#108
0"
#109
b110001 $
1"
#110
0"
#111
b110010 $
1"
#112
0"
#113
b110011 $
1"
#114
0"
#115
b110100 $
1"
#116
0"
#117
b110101 $
1"
#118
0"
#119
b110110 $
1"
#120
0"
#121
b110111 $
1"
#122
0"
#123
b111000 $
1"
#124
0"
#125
b111001 $
1"
#126
0"
#127
b111010 $
1"
#128
0"
#129
b111011 $
1"
#130
0"
#131
b111100 $
1"
#132
0"
#133
b111101 $
1"
#134
0"
#135
b111110 $
1"
#136
0"
#137
b111111 $
1"
#138
0"
#139
b1000000 $
1"
#140
0"
#141
b1000001 $
1"
#142
0"
#143
b1000010 $
1"
#144
0"
#145
b1000011 $
1"
#146
0"
#147
b1000100 $
1"
#148
0"
#149
b1000101 $
1"
#150
0"
#151
b1000110 $
1"
#152
0"
#153
b1000111 $
1"
#154
0"
#155
b1001000 $
1"
#156
0"
#157
b1001001 $
1"
#158
0"
#159
b1001010 $
1"
#160
0"
#161
b1001011 $
1"
#162
0"
#163
b1001100 $
1"
#164
0"
#165
b1001101 $
1"
#166
0"
#167
b1001110 $
1"
#168
0"
#169
b1001111 $
1"
#170
0"
#171
b1010000 $
1"
#172
0"
#173
b1010001 $
1"
#174
0"
#175
b1010010 $
1"
#176
0"
#177
b1010011 $
1"
#178
0"
#179
b1010100 $
1"
#180
0"
#181
b1010101 $
1"
#182
0"
#183
b1010110 $
1"
#184
0"
#185
b1010111 $
1"
#186
0"
#187
b1011000 $
1"
#188
0"
#189
b1011001 $
1"
#190
0"
#191
b1011010 $
1"
#192
0"
#193
b1011011 $
1"
#194
0"
#195
b1011100 $
1"
#196
0"
#197
b1011101 $
1"
#198
0"
#199
b1011110 $
1"
#200
0"
#201
b1011111 $
1"
#202
0"
#203
b1100000 $
1"
#204
0"
#205
b1100001 $
1"
#206
0"
#207
b1100010 $
1"
#208
0"
#209
b1100011 $
1"
#210
0"
0#
#211
b1100111 $
1"
