divisor_modificado/baudgen.vh
//-- Fichero baudgen.vh
`define B115200 104
`define B57600  208
`define B38400  313

`define B19200  625
`define B9600   1250
`define B4800   2500
`define B2400   5000
`define B1200   10000
`define B600    20000
`define B300    40000

_divisorM/div.v
module div(clk_i, clk_o);
  input wire clk_i;
  output wire clk_o;

  parameter M = 12_000_000;
  localparam N = $clog2(M);

  reg [N-1:0] cont = 0;

  always @ (posedge clk_i)
    if (cont == M-1)
      cont <= 0;
    else
      cont <= cont + 1;

  assign clk_o = cont[N-1];

endmodule //

_baudios_tx/baud.v
`include "baudgen.vh"

module baud(clk,load,tx);
  input wire clk;
  output wire tx;
  input wire load;
  wire clk_baud;
  reg [9:0] shifter = 0;

  parameter M = `B115200;

  div # (.M(M))
    BAUD (
      .clk_i(clk),
      .clk_o(clk_baud)
      );

  assign tx = (load == 0) ? 1:shifter[0]; // tx=1 si load=0 sino tx=shifter[0]

  always @ (posedge clk_baud)
    if (load == 0)
      shifter <= {"C",2'b01}; // Primero se envia el '1' luego el bit '0'(start)
                              // y a continuacion el codigo de "C" del lsb al msb
    else
      shifter <= {shifter[0],shifter[9:1]};


endmodule //

_baudios_tx/baud_tb.v
module baud_tb();
  reg clk = 0;
  wire tx;
  reg load = 0;

  baud # (.M(5))
    dut(
      .clk(clk),
      .load(load),
      .tx(tx)
      );

  always #1 clk <= ~clk;

  initial begin
    $dumpfile("baud_tb.vcd");
    $dumpvars(0,baud_tb);
    #10 load <= 0;
    #15 load <=1;
    #400 $display("FIN");
    $finish;
  end

endmodule //

_baudios_tx/baud_tb.vcd
$date
	Sun Sep 22 21:56:51 2019
$end
$version
	Icarus Verilog
$end
$timescale
	1s
$end
$scope module baud_tb $end
$var wire 1 ! tx $end
$var reg 1 " clk $end
$var reg 1 # load $end
$scope module dut $end
$var wire 1 " clk $end
$var wire 1 # load $end
$var wire 1 ! tx $end
$var wire 1 $ clk_baud $end
$var reg 10 % shifter [9:0] $end
$scope module BAUD $end
$var wire 1 " clk_i $end
$var wire 1 $ clk_o $end
$var reg 3 & cont [2:0] $end
$upscope $end
$upscope $end
$upscope $end
$enddefinitions $end
#0
$dumpvars
b0 &
b0 %
0$
0#
0"
1!
$end
#1
b1 &
1"
#2
0"
#3
b10 &
1"
#4
0"
#5
b11 &
1"
#6
0"
#7
b100001101 %
1$
b100 &
1"
#8
0"
#9
0$
b0 &
1"
#10
0"
#11
b1 &
1"
#12
0"
#13
b10 &
1"
#14
0"
#15
b11 &
1"
#16
0"
#17
1$
b100 &
1"
#18
0"
#19
0$
b0 &
1"
#20
0"
#21
b1 &
1"
#22
0"
#23
b10 &
1"
#24
0"
#25
b11 &
1"
1#
#26
0"
#27
0!
b1010000110 %
1$
b100 &
1"
#28
0"
#29
0$
b0 &
1"
#30
0"
#31
b1 &
1"
#32
0"
#33
b10 &
1"
#34
0"
#35
b11 &
1"
#36
0"
#37
1!
b101000011 %
1$
b100 &
1"
#38
0"
#39
0$
b0 &
1"
#40
0"
#41
b1 &
1"
#42
0"
#43
b10 &
1"
#44
0"
#45
b11 &
1"
#46
0"
#47
b1010100001 %
1$
b100 &
1"
#48
0"
#49
0$
b0 &
1"
#50
0"
#51
b1 &
1"
#52
0"
#53
b10 &
1"
#54
0"
#55
b11 &
1"
#56
0"
#57
0!
b1101010000 %
1$
b100 &
1"
#58
0"
#59
0$
b0 &
1"
#60
0"
#61
b1 &
1"
#62
0"
#63
b10 &
1"
#64
0"
#65
b11 &
1"
#66
0"
#67
b110101000 %
1$
b100 &
1"
#68
0"
#69
0$
b0 &
1"
#70
0"
#71
b1 &
1"
#72
0"
#73
b10 &
1"
#74
0"
#75
b11 &
1"
#76
0"
#77
b11010100 %
1$
b100 &
1"
#78
0"
#79
0$
b0 &
1"
#80
0"
#81
b1 &
1"
#82
0"
#83
b10 &
1"
#84
0"
#85
b11 &
1"
#86
0"
#87
b1101010 %
1$
b100 &
1"
#88
0"
#89
0$
b0 &
1"
#90
0"
#91
b1 &
1"
#92
0"
#93
b10 &
1"
#94
0"
#95
b11 &
1"
#96
0"
#97
1!
b110101 %
1$
b100 &
1"
#98
0"
#99
0$
b0 &
1"
#100
0"
#101
b1 &
1"
#102
0"
#103
b10 &
1"
#104
0"
#105
b11 &
1"
#106
0"
#107
0!
b1000011010 %
1$
b100 &
1"
#108
0"
#109
0$
b0 &
1"
#110
0"
#111
b1 &
1"
#112
0"
#113
b10 &
1"
#114
0"
#115
b11 &
1"
#116
0"
#117
1!
b100001101 %
1$
b100 &
1"
#118
0"
#119
0$
b0 &
1"
#120
0"
#121
b1 &
1"
#122
0"
#123
b10 &
1"
#124
0"
#125
b11 &
1"
#126
0"
#127
0!
b1010000110 %
1$
b100 &
1"
#128
0"
#129
0$
b0 &
1"
#130
0"
#131
b1 &
1"
#132
0"
#133
b10 &
1"
#134
0"
#135
b11 &
1"
#136
0"
#137
1!
b101000011 %
1$
b100 &
1"
#138
0"
#139
0$
b0 &
1"
#140
0"
#141
b1 &
1"
#142
0"
#143
b10 &
1"
#144
0"
#145
b11 &
1"
#146
0"
#147
b1010100001 %
1$
b100 &
1"
#148
0"
#149
0$
b0 &
1"
#150
0"
#151
b1 &
1"
#152
0"
#153
b10 &
1"
#154
0"
#155
b11 &
1"
#156
0"
#157
0!
b1101010000 %
1$
b100 &
1"
#158
0"
#159
0$
b0 &
1"
#160
0"
#161
b1 &
1"
#162
0"
#163
b10 &
1"
#164
0"
#165
b11 &
1"
#166
0"
#167
b110101000 %
1$
b100 &
1"
#168
0"
#169
0$
b0 &
1"
#170
0"
#171
b1 &
1"
#172
0"
#173
b10 &
1"
#174
0"
#175
b11 &
1"
#176
0"
#177
b11010100 %
1$
b100 &
1"
#178
0"
#179
0$
b0 &
1"
#180
0"
#181
b1 &
1"
#182
0"
#183
b10 &
1"
#184
0"
#185
b11 &
1"
#186
0"
#187
b1101010 %
1$
b100 &
1"
#188
0"
#189
0$
b0 &
1"
#190
0"
#191
b1 &
1"
#192
0"
#193
b10 &
1"
#194
0"
#195
b11 &
1"
#196
0"
#197
1!
b110101 %
1$
b100 &
1"
#198
0"
#199
0$
b0 &
1"
#200
0"
#201
b1 &
1"
#202
0"
#203
b10 &
1"
#204
0"
#205
b11 &
1"
#206
0"
#207
0!
b1000011010 %
1$
b100 &
1"
#208
0"
#209
0$
b0 &
1"
#210
0"
#211
b1 &
1"
#212
0"
#213
b10 &
1"
#214
0"
#215
b11 &
1"
#216
0"
#217
1!
b100001101 %
1$
b100 &
1"
#218
0"
#219
0$
b0 &
1"
#220
0"
#221
b1 &
1"
#222
0"
#223
b10 &
1"
#224
0"
#225
b11 &
1"
#226
0"
#227
0!
b1010000110 %
1$
b100 &
1"
#228
0"
#229
0$
b0 &
1"
#230
0"
#231
b1 &
1"
#232
0"
#233
b10 &
1"
#234
0"
#235
b11 &
1"
#236
0"
#237
1!
b101000011 %
1$
b100 &
1"
#238
0"
#239
0$
b0 &
1"
#240
0"
#241
b1 &
1"
#242
0"
#243
b10 &
1"
#244
0"
#245
b11 &
1"
#246
0"
#247
b1010100001 %
1$
b100 &
1"
#248
0"
#249
0$
b0 &
1"
#250
0"
#251
b1 &
1"
#252
0"
#253
b10 &
1"
#254
0"
#255
b11 &
1"
#256
0"
#257
0!
b1101010000 %
1$
b100 &
1"
#258
0"
#259
0$
b0 &
1"
#260
0"
#261
b1 &
1"
#262
0"
#263
b10 &
1"
#264
0"
#265
b11 &
1"
#266
0"
#267
b110101000 %
1$
b100 &
1"
#268
0"
#269
0$
b0 &
1"
#270
0"
#271
b1 &
1"
#272
0"
#273
b10 &
1"
#274
0"
#275
b11 &
1"
#276
0"
#277
b11010100 %
1$
b100 &
1"
#278
0"
#279
0$
b0 &
1"
#280
0"
#281
b1 &
1"
#282
0"
#283
b10 &
1"
#284
0"
#285
b11 &
1"
#286
0"
#287
b1101010 %
1$
b100 &
1"
#288
0"
#289
0$
b0 &
1"
#290
0"
#291
b1 &
1"
#292
0"
#293
b10 &
1"
#294
0"
#295
b11 &
1"
#296
0"
#297
1!
b110101 %
1$
b100 &
1"
#298
0"
#299
0$
b0 &
1"
#300
0"
#301
b1 &
1"
#302
0"
#303
b10 &
1"
#304
0"
#305
b11 &
1"
#306
0"
#307
0!
b1000011010 %
1$
b100 &
1"
#308
0"
#309
0$
b0 &
1"
#310
0"
#311
b1 &
1"
#312
0"
#313
b10 &
1"
#314
0"
#315
b11 &
1"
#316
0"
#317
1!
b100001101 %
1$
b100 &
1"
#318
0"
#319
0$
b0 &
1"
#320
0"
#321
b1 &
1"
#322
0"
#323
b10 &
1"
#324
0"
#325
b11 &
1"
#326
0"
#327
0!
b1010000110 %
1$
b100 &
1"
#328
0"
#329
0$
b0 &
1"
#330
0"
#331
b1 &
1"
#332
0"
#333
b10 &
1"
#334
0"
#335
b11 &
1"
#336
0"
#337
1!
b101000011 %
1$
b100 &
1"
#338
0"
#339
0$
b0 &
1"
#340
0"
#341
b1 &
1"
#342
0"
#343
b10 &
1"
#344
0"
#345
b11 &
1"
#346
0"
#347
b1010100001 %
1$
b100 &
1"
#348
0"
#349
0$
b0 &
1"
#350
0"
#351
b1 &
1"
#352
0"
#353
b10 &
1"
#354
0"
#355
b11 &
1"
#356
0"
#357
0!
b1101010000 %
1$
b100 &
1"
#358
0"
#359
0$
b0 &
1"
#360
0"
#361
b1 &
1"
#362
0"
#363
b10 &
1"
#364
0"
#365
b11 &
1"
#366
0"
#367
b110101000 %
1$
b100 &
1"
#368
0"
#369
0$
b0 &
1"
#370
0"
#371
b1 &
1"
#372
0"
#373
b10 &
1"
#374
0"
#375
b11 &
1"
#376
0"
#377
b11010100 %
1$
b100 &
1"
#378
0"
#379
0$
b0 &
1"
#380
0"
#381
b1 &
1"
#382
0"
#383
b10 &
1"
#384
0"
#385
b11 &
1"
#386
0"
#387
b1101010 %
1$
b100 &
1"
#388
0"
#389
0$
b0 &
1"
#390
0"
#391
b1 &
1"
#392
0"
#393
b10 &
1"
#394
0"
#395
b11 &
1"
#396
0"
#397
1!
b110101 %
1$
b100 &
1"
#398
0"
#399
0$
b0 &
1"
#400
0"
#401
b1 &
1"
#402
0"
#403
b10 &
1"
#404
0"
#405
b11 &
1"
#406
0"
#407
0!
b1000011010 %
1$
b100 &
1"
#408
0"
#409
0$
b0 &
1"
#410
0"
#411
b1 &
1"
#412
0"
#413
b10 &
1"
#414
0"
#415
b11 &
1"
#416
0"
#417
1!
b100001101 %
1$
b100 &
1"
#418
0"
#419
0$
b0 &
1"
#420
0"
#421
b1 &
1"
#422
0"
#423
b10 &
1"
#424
0"
#425
b11 &
1"
