_divisorM/div.v
module div(clk_i, clk_o);
  input wire clk_i;
  output wire clk_o;

  parameter M = 12_000_000;
  localparam N = $clog2(M);

  reg [N-1:0] cont = 0;

  always @ (posedge clk_i)
    if (cont == M-1)
      cont <= 0;
    else
      cont <= cont + 1;

  assign clk_o = cont[N-1];

endmodule //

_divisorM/div_tb.v
module div_tb();
  reg clk = 0;
  wire clk3;

  div #(7)
    DIV(
      .clk_i(clk),
      .clk_o(clkM)
      );

  always #1 clk = ~clk;

  initial begin
    $dumpfile("div_tb.vcd");
    $dumpvars(0,div_tb);
    #50 $display("Fin");
    $finish;
  end
endmodule //

_divisorM/div_tb.vcd
$date
	Sat Sep 21 15:50:05 2019
$end
$version
	Icarus Verilog
$end
$timescale
	1s
$end
$scope module div_tb $end
$var wire 1 ! clkM $end
$var reg 1 " clk $end
$scope module DIV $end
$var wire 1 " clk_i $end
$var wire 1 ! clk_o $end
$var reg 3 # cont [2:0] $end
$upscope $end
$upscope $end
$enddefinitions $end
#0
$dumpvars
b0 #
0"
0!
$end
#1
b1 #
1"
#2
0"
#3
b10 #
1"
#4
0"
#5
b11 #
1"
#6
0"
#7
1!
b100 #
1"
#8
0"
#9
b101 #
1"
#10
0"
#11
b110 #
1"
#12
0"
#13
0!
b0 #
1"
#14
0"
#15
b1 #
1"
#16
0"
#17
b10 #
1"
#18
0"
#19
b11 #
1"
#20
0"
#21
1!
b100 #
1"
#22
0"
#23
b101 #
1"
#24
0"
#25
b110 #
1"
#26
0"
#27
0!
b0 #
1"
#28
0"
#29
b1 #
1"
#30
0"
#31
b10 #
1"
#32
0"
#33
b11 #
1"
#34
0"
#35
1!
b100 #
1"
#36
0"
#37
b101 #
1"
#38
0"
#39
b110 #
1"
#40
0"
#41
0!
b0 #
1"
#42
0"
#43
b1 #
1"
#44
0"
#45
b10 #
1"
#46
0"
#47
b11 #
1"
#48
0"
#49
1!
b100 #
1"
