registro/prescaler.v
module prescaler (clk_in,clk_out);
  input clk_in;
  output clk_out;
  wire clk_out;
  wire clk_in;

  parameter N = 22;

  reg [N-1 : 0] count = 0;

  always @ ( posedge clk_in) begin
    count <= count + 1;
  end

  assign clk_out = count[N-1];

endmodule //

ini_registro/reg_i.v
module reg_i (clk, dato);
  input wire clk;
  output wire [7:0] dato;

  parameter INI = 8'b00001111;
  parameter N0 = 19;

  reg sel = 0;
  reg [7:0] dout;
  wire [7:0] din;
  wire clk_base;

  always @ (posedge clk_base)                  // Registro
    dout <= din;

  assign dato = dout;

  assign din = (sel == 0) ? INI : ~dout;   // MUX

  always @ (posedge clk_base)            // Inicializador
    sel <= 1;

  prescaler #(.N(N0))
    PRE(
      .clk_in(clk),                     // Prescaler
      .clk_out(clk_base)
      );

endmodule //

ini_registro/reg_i_tb.v
module reg_i_tb ();
  reg clk = 0;
  wire [7:0] data;

  reg_i #(.N0(1))
    test(
      .clk(clk),
      .dato(data)
      );

  always #1 clk = ~clk;

  initial begin
   $dumpfile("reg_i_tb.vcd");
   $dumpvars(0,reg_i_tb);
   #30 $display("Fin de la sim.");
   $finish;
  end

endmodule //

ini_registro/reg_i_tb.vcd
$date
	Thu Sep 19 21:35:54 2019
$end
$version
	Icarus Verilog
$end
$timescale
	1s
$end
$scope module reg_i_tb $end
$var wire 8 ! data [7:0] $end
$var reg 1 " clk $end
$scope module test $end
$var wire 1 " clk $end
$var wire 8 # dato [7:0] $end
$var wire 8 $ din [7:0] $end
$var wire 1 % clk_base $end
$var reg 8 & dout [7:0] $end
$var reg 1 ' sel $end
$scope module PRE $end
$var wire 1 " clk_in $end
$var wire 1 % clk_out $end
$var reg 1 ( count $end
$upscope $end
$upscope $end
$upscope $end
$enddefinitions $end
#0
$dumpvars
0(
0'
bx &
0%
b1111 $
bx #
0"
bx !
$end
#1
b11110000 $
b1111 !
b1111 #
b1111 &
1'
1%
1(
1"
#2
0"
#3
0%
0(
1"
#4
0"
#5
b1111 $
b11110000 !
b11110000 #
b11110000 &
1%
1(
1"
#6
0"
#7
0%
0(
1"
#8
0"
#9
b11110000 $
b1111 !
b1111 #
b1111 &
1%
1(
1"
#10
0"
#11
0%
0(
1"
#12
0"
#13
b1111 $
b11110000 !
b11110000 #
b11110000 &
1%
1(
1"
#14
0"
#15
0%
0(
1"
#16
0"
#17
b11110000 $
b1111 !
b1111 #
b1111 &
1%
1(
1"
#18
0"
#19
0%
0(
1"
#20
0"
#21
b1111 $
b11110000 !
b11110000 #
b11110000 &
1%
1(
1"
#22
0"
#23
0%
0(
1"
#24
0"
#25
b11110000 $
b1111 !
b1111 #
b1111 &
1%
1(
1"
#26
0"
#27
0%
0(
1"
#28
0"
#29
b1111 $
b11110000 !
b11110000 #
b11110000 &
1%
1(
1"
